geocodio/__init__.py
geocodio/client.py
geocodio/data.py
geocodio/exceptions.py
pygeocodio-1.5.0.dist-info/METADATA
pygeocodio-1.5.0.dist-info/WHEEL
pygeocodio-1.5.0.dist-info/licenses/AUTHORS.rst
pygeocodio-1.5.0.dist-info/licenses/LICENSE
pygeocodio-1.5.0.dist-info/RECORD
