Metadata-Version: 2.4
Name: pygeocodio
Version: 1.5.0
Summary: Python wrapper for Geocod.io API
Project-URL: Homepage, https://github.com/bennylope/pygeocodio
Author-email: Ben Lopatin <ben@benlopatin.com>
License: BSD
License-File: AUTHORS.rst
License-File: LICENSE
Keywords: geocodio
Classifier: Development Status :: 5 - Production/Stable
Classifier: Intended Audience :: Developers
Classifier: License :: OSI Approved :: BSD License
Classifier: Natural Language :: English
Classifier: Programming Language :: Python :: 3
Classifier: Programming Language :: Python :: 3.9
Classifier: Programming Language :: Python :: 3.10
Classifier: Programming Language :: Python :: 3.11
Classifier: Programming Language :: Python :: 3.12
Classifier: Programming Language :: Python :: 3.13
Classifier: Topic :: Internet :: WWW/HTTP
Requires-Python: >=3.9
Requires-Dist: requests>=1.0.0
Provides-Extra: dev
Requires-Dist: pre-commit>=4.2.0; extra == 'dev'
Provides-Extra: docs
Requires-Dist: sphinx==7.0.1; extra == 'docs'
Provides-Extra: tests
Requires-Dist: httpretty>=0.9.7; extra == 'tests'
Requires-Dist: pytest-cov>=4.0; extra == 'tests'
Requires-Dist: pytest>=7.0; extra == 'tests'
Requires-Dist: requests>=1.0.0; extra == 'tests'
